{"abdmors": ["abdmors", "ab", "abdmor", "abdor", "abdors", "abdr", "abdrs", "abds", "abm", "abmo", "abmor", "abmors", "abmos", "abmr", "abmrs", "abms", "abo", "abor", "abors", "abos", "abr", "abrs", "abs", "ad", "adm", "admor", "admors", "admr", "admrs", "adms", "ado", "ador", "adors", "ados", "adr", "adrs", "ads", "am", "amo", "amor", "amors", "amos", "amr", "amrs", "ams", "aor", "aors", "ars", "as", "bdmr", "bdor", "bdors", "bdos", "bmo", "bmor", "bmors", "bmos", "bo", "bor", "bors", "bos", "dmo", "dmor", "dmors", "dmos", "do", "dor", "dors", "dos", "mor", "mors", "mos"], "abdmnr": ["abdmnr", "ab", "abdmn", "abdn", "abdnr", "abdr", "abm", "abmnr", "abmr", "abn", "abnr", "abr", "ad", "adm", "admn", "admnr", "admr", "adnr", "adr", "am", "amn", "amr", "an", "bdmr"], "abdmnrs": ["abdmnrs", "ab", "abdmn", "abdmnr", "abdmns", "abdn", "abdnr", "abdnrs", "abdns", "abdr", "abdrs", "abds", "abm", "abmnr", "abmr", "abmrs", "abms", "abn", "abnr", "abnrs", "abns", "abr", "abrs", "abs", "ad", "adm", "admn", "admnr", "admnrs", "admns", "admr", "admrs", "adms", "adnr", "adnrs", "adns", "adr", "adrs", "ads", "am", "amn", "amns", "amr", "amrs", "ams", "an", "anrs", "ans", "ars", "as", "bdmr"], "abdmn": ["abdmn", "ab", "abdn", "abm", "abn", "ad", "adm", "admn", "am", "amn", "an"], "abdmns": ["abdmns", "ab", "abdmn", "abdn", "abdns", "abds", "abm", "abms", "abn", "abns", "abs", "ad", "adm", "admn", "admns", "adms", "adns", "ads", "am", "amn", "amns", "ams", "an", "ans", "as"], "abdmnru": ["abdmnru", "ab", "abdmn", "abdmnr", "abdn", "abdnr", "abdr", "abdru", "abdu", "abm", "abmnr", "abmr", "abmru", "abn", "abnr", "abnru", "abr", "abu", "ad", "adm", "admn", "admnr", "admnu", "admr", "admru", "admu", "adnr", "adr", "adru", "adu", "am", "amn", "amnru", "amnu", "amr", "amru", "an", "anru", "aru", "bdmr", "bdmu", "bdnu", "bdru", "bmnu", "bnru", "bru", "dmru", "dmu", "dru", "mru", "mu"], "abdmor": ["abdmor", "ab", "abdor", "abdr", "abm", "abmo", "abmor", "abmr", "abo", "abor", "abr", "ad", "adm", "admor", "admr", "ado", "ador", "adr", "am", "amo", "amor", "amr", "aor", "bdmr", "bdor", "bmo", "bmor", "bo", "bor", "dmo", "dmor", "do", "dor", "mor"], "abdmnor": ["abdmnor", "ab", "abdmn", "abdmno", "abdmnr", "abdmor", "abdn", "abdno", "abdnor", "abdnr", "abdor", "abdr", "abm", "abmnr", "abmo", "abmor", "abmr", "abn", "abno", "abnor", "abnr", "abo", "abor", "abr", "ad", "adm", "admn", "admno", "admnor", "admnr", "admor", "admr", "adno", "adnor", "adnr", "ado", "ador", "adr", "am", "amn", "amno", "amnor", "amo", "amor", "amr", "an", "ano", "anor", "aor", "bdmr", "bdno", "bdor", "bmo", "bmor", "bno", "bnor", "bo", "bor", "dmnor", "dmo", "dmor", "dnor", "do", "dor", "mno", "mnor", "mor", "no"], "abdmno": ["abdmno", "ab", "abdmn", "abdn", "abdno", "abm", "abmo", "abn", "abno", "abo", "ad", "adm", "admn", "admno", "adno", "ado", "am", "amn", "amno", "amo", "an", "ano", "bdno", "bmo", "bno", "bo", "dmo", "do", "mno", "no"], "abdmnos": ["abdmnos", "ab", "abdmn", "abdmno", "abdmns", "abdn", "abdno", "abdnos", "abdns", "abds", "abm", "abmo", "abmos", "abms", "abn", "abno", "abnos", "abns", "abo", "abos", "abs", "ad", "adm", "admn", "admno", "admnos", "admns", "adms", "adno", "adnos", "adns", "ado", "ados", "ads", "am", "amn", "amno", "amnos", "amns", "amo", "amos", "ams", "an", "ano", "anos", "ans", "as", "bdno", "bdnos", "bdos", "bmo", "bmos", "bno", "bnos", "bo", "bos", "dmo", "dmos", "dnos", "do", "dos", "mno", "mnos", "mos", "no", "nos"], "abdmnow": ["abdmnow", "ab", "abdmn", "abdmno", "abdn", "abdno", "abdw", "abm", "abmnow", "abmo", "abn", "abno", "abnw", "abo", "ad", "adm", "admn", "admno", "admnow", "adno", "adnow", "adnw", "ado", "adow", "am", "amn", "amno", "amnow", "amo", "an", "ano", "anw", "bdno", "bmo", "bmow", "bno", "bo", "bow", "dmo", "dnow", "do", "dow", "mno", "no"], "abdmopr": ["abdmopr", "ab", "abdmor", "abdor", "abdr", "abm", "abmo", "abmor", "abmp", "abmr", "abo", "abor", "abr", "ad", "adm", "admop", "admor", "admp", "admr", "ado", "adop", "adopr", "ador", "adpr", "adr", "am", "amo", "amopr", "amor", "amp", "ampr", "amr", "aop", "aopr", "aor", "ap", "apr", "bdmr", "bdor", "bmo", "bmor", "bo", "bopr", "bor", "dmo", "dmor", "do", "dop", "dopr", "dor", "mop", "mopr", "mor", "op", "opr"], "abdmort": ["abdmort", "ab", "abdmor", "abdor", "abdort", "abdr", "abdrt", "abm", "abmo", "abmor", "abmort", "abmr", "abo", "abor", "abort", "abot", "abr", "abrt", "abt", "ad", "adm", "admor", "admort", "admr", "ado", "ador", "adort", "adot", "adr", "adrt", "adt", "am", "amo", "amor", "amort", "amot", "amr", "amrt", "aor", "aort", "aot", "art", "bdmr", "bdor", "bdot", "bmo", "bmor", "bmot", "bo", "bor", "bort", "bot", "dmo", "dmor", "do", "dor", "dort", "mor", "mort", "mot", "ort", "ot"]}