{"aemnsu": ["aemnsu", "aemn", "aemns", "aems", "aemsu", "aens", "aensu", "aes", "am", "amn", "amns", "amnsu", "amnu", "ams", "amsu", "an", "ans", "ansu", "as", "em", "emn", "emns", "emnsu", "emnu", "ems", "emsu", "ens", "ensu", "es", "esu", "msu", "mu", "nsu", "su"], "aemnst": ["aemnst", "aemn", "aemns", "aemnt", "aems", "aemst", "aemt", "aens", "aenst", "aent", "aes", "aest", "aet", "am", "amn", "amns", "amnst", "amnt", "ams", "amst", "an", "ans", "anst", "ant", "as", "ast", "em", "emn", "emns", "emnst", "emnt", "ems", "emst", "emt", "ens", "enst", "ent", "es", "est"], "aemntz": ["aemntz", "aemn", "aemnt", "aemt", "aemz", "aent", "aenz", "aet", "aetz", "am", "amn", "amnt", "an", "ant", "anz", "atz", "em", "emn", "emnt", "emt", "ent"], "aemn": ["aemn", "am", "amn", "an", "em", "emn"], "aemnt": ["aemnt", "aemn", "aemt", "aent", "aet", "am", "amn", "amnt", "an", "ant", "em", "emn", "emnt", "emt", "ent"], "aemnot": ["aemnot", "aemn", "aemno", "aemnt", "aemt", "aenot", "aent", "aeot", "aet", "am", "amn", "amno", "amnot", "amnt", "amo", "amot", "an", "ano", "anot", "ant", "aot", "em", "emn", "emno", "emnot", "emnt", "emo", "emot", "emt", "eno", "enot", "ent", "eot", "mno", "mot", "no", "not", "ot"], "aemnsty": ["aemnsty", "aemn", "aemns", "aemnst", "aemnt", "aemny", "aems", "aemst", "aemsty", "aemsy", "aemt", "aemty", "aemy", "aens", "aenst", "aensty", "aensy", "aent", "aenty", "aeny", "aes", "aest", "aesty", "aesy", "aet", "am", "amn", "amns", "amnst", "amnsy", "amnt", "amny", "ams", "amst", "amsty", "amsy", "amty", "amy", "an", "ans", "anst", "ansty", "ansy", "ant", "anty", "any", "as", "ast", "asty", "asy", "aty", "em", "emn", "emns", "emnst", "emnt", "emny", "ems", "emst", "emsty", "emsy", "emt", "ens", "enst", "ensy", "ent", "enty", "es", "est", "esty", "esy", "sty"], "aemnstu": ["aemnstu", "aemn", "aemns", "aemnst", "aemnsu", "aemnt", "aemntu", "aems", "aemst", "aemstu", "aemsu", "aemt", "aemtu", "aens", "aenst", "aenstu", "aensu", "aent", "aentu", "aes", "aest", "aestu", "aet", "am", "amn", "amns", "amnst", "amnstu", "amnsu", "amnt", "amntu", "amnu", "ams", "amst", "amstu", "amsu", "an", "ans", "anst", "anstu", "ansu", "ant", "antu", "as", "ast", "astu", "atu", "em", "emn", "emns", "emnst", "emnstu", "emnsu", "emnt", "emntu", "emnu", "ems", "emst", "emstu", "emsu", "emt", "emtu", "ens", "enst", "enstu", "ensu", "ent", "entu", "es", "est", "estu", "esu", "mstu", "msu", "mtu", "mu", "nstu", "nsu", "stu", "su", "tu"], "aemns": ["aemns", "aemn", "aems", "aens", "aes", "am", "amn", "amns", "ams", "an", "ans", "as", "em", "emn", "emns", "ems", "ens", "es"], "aemnost": ["aemnost", "aemn", "aemno", "aemnos", "aemnot", "aemns", "aemnst", "aemnt", "aemost", "aems", "aemst", "aemt", "aenos", "aenost", "aenot", "aens", "aenst", "aent", "aeos", "aeost", "aeot", "aes", "aest", "aet", "am", "amn", "amno", "amnos", "amnost", "amnot", "amns", "amnst", "amnt", "amo", "amos", "amost", "amot", "ams", "amst", "an", "ano", "anos", "anost", "anot", "ans", "anst", "ant", "aost", "aot", "as", "ast", "em", "emn", "emno", "emnos", "emnost", "emnot", "emns", "emnst", "emnt", "emo", "emos", "emost", "emot", "ems", "emst", "emt", "eno", "enos", "enost", "enot", "ens", "enst", "ent", "eos", "eost", "eot", "es", "est", "mno", "mnos", "mos", "most", "mot", "no", "nos", "nost", "not", "ost", "ot"], "aemnort": ["aemnort", "aemn", "aemno", "aemnor", "aemnot", "aemnr", "aemnrt", "aemnt", "aemor", "aemort", "aemr", "aemrt", "aemt", "aenor", "aenort", "aenot", "aenr", "aenrt", "aent", "aeor", "aeort", "aeot", "aer", "aert", "aet", "am", "amn", "amno", "amnor", "amnort", "amnot", "amnrt", "amnt", "amo", "amor", "amort", "amot", "amr", "amrt", "an", "ano", "anor", "anort", "anot", "anrt", "ant", "aor", "aort", "aot", "art", "em", "emn", "emno", "emnor", "emnort", "emnot", "emnr", "emnt", "emo", "emor", "emort", "emot", "emr", "emrt", "emt", "eno", "enort", "enot", "enr", "enrt", "ent", "eor", "eort", "eot", "ert", "mno", "mnor", "mor", "mort", "mot", "no", "nort", "not", "ort", "ot"], "aemno": ["aemno", "aemn", "am", "amn", "amno", "amo", "an", "ano", "em", "emn", "emno", "emo", "eno", "mno", "no"], "aemnos": ["aemnos", "aemn", "aemno", "aemns", "aems", "aenos", "aens", "aeos", "aes", "am", "amn", "amno", "amnos", "amns", "amo", "amos", "ams", "an", "ano", "anos", "ans", "as", "em", "emn", "emno", "emnos", "emns", "emo", "emos", "ems", "eno", "enos", "ens", "eos", "es", "mno", "mnos", "mos", "no", "nos"], "aemnory": ["aemnory", "aemn", "aemno", "aemnor", "aemnoy", "aemnr", "aemny", "aemor", "aemr", "aemry", "aemy", "aenor", "aenoy", "aenr", "aenry", "aeny", "aeor", "aer", "aery", "am", "amn", "amno", "amnor", "amnoy", "amny", "amo", "amor", "amory", "amoy", "amr", "amry", "amy", "an", "ano", "anor", "anory", "anoy", "anry", "any", "aor", "aory", "ary", "em", "emn", "emno", "emnor", "emnory", "emnoy", "emnr", "emny", "emo", "emor", "emory", "emr", "emry", "eno", "enory", "enr", "eor", "eory", "ery", "mno", "mnor", "mnoy", "mor", "mory", "moy", "no"], "aemnprt": ["aemnprt", "aemn", "aemnp", "aemnr", "aemnrt", "aemnt", "aempr", "aemprt", "aempt", "aemr", "aemrt", "aemt", "aenp", "aenpr", "aenprt", "aenpt", "aenr", "aenrt", "aent", "aepr", "aeprt", "aept", "aer", "aert", "aet", "am", "amn", "amnp", "amnprt", "amnrt", "amnt", "amp", "ampr", "amprt", "ampt", "amr", "amrt", "an", "anpr", "anprt", "anpt", "anrt", "ant", "ap", "apr", "aprt", "art", "em", "emn", "emnp", "emnr", "emnt", "empr", "emprt", "empt", "emr", "emrt", "emt", "enp", "enpr", "enprt", "enpt", "enr", "enrt", "ent", "ep", "epr", "eprt", "ept", "ert"], "aemnp": ["aemnp", "aemn", "aenp", "am", "amn", "amnp", "amp", "an", "ap", "em", "emn", "emnp", "enp", "ep"], "aemnpst": ["aemnpst", "aemn", "aemnp", "aemns", "aemnst", "aemnt", "aempst", "aempt", "aems", "aemst", "aemt", "aenp", "aenps", "aenpst", "aenpt", "aens", "aenst", "aent", "aeps", "aepst", "aept", "aes", "aest", "aet", "am", "amn", "amnp", "amnps", "amns", "amnst", "amnt", "amp", "amps", "ampst", "ampt", "ams", "amst", "an", "anps", "anpst", "anpt", "ans", "anst", "ant", "ap", "aps", "apst", "as", "ast", "em", "emn", "emnp", "emns", "emnst", "emnt", "empst", "empt", "ems", "emst", "emt", "enp", "enps", "enpst", "enpt", "ens", "enst", "ent", "ep", "eps", "epst", "ept", "es", "est", "pst"], "aemnrt": ["aemnrt", "aemn", "aemnr", "aemnt", "aemr", "aemrt", "aemt", "aenr", "aenrt", "aent", "aer", "aert", "aet", "am", "amn", "amnrt", "amnt", "amr", "amrt", "an", "anrt", "ant", "art", "em", "emn", "emnr", "emnt", "emr", "emrt", "emt", "enr", "enrt", "ent", "ert"], "aemnrst": ["aemnrst", "aemn", "aemnr", "aemnrs", "aemnrt", "aemns", "aemnst", "aemnt", "aemr", "aemrs", "aemrst", "aemrt", "aems", "aemst", "aemt", "aenr", "aenrs", "aenrst", "aenrt", "aens", "aenst", "aent", "aer", "aers", "aerst", "aert", "aes", "aest", "aet", "am", "amn", "amnrst", "amnrt", "amns", "amnst", "amnt", "amr", "amrs", "amrst", "amrt", "ams", "amst", "an", "anrs", "anrst", "anrt", "ans", "anst", "ant", "ars", "arst", "art", "as", "ast", "em", "emn", "emnr", "emnrst", "emns", "emnst", "emnt", "emr", "emrs", "emrst", "emrt", "ems", "emst", "emt", "enr", "enrs", "enrst", "enrt", "ens", "enst", "ent", "ers", "erst", "ert", "es", "est"], "aemntu": ["aemntu", "aemn", "aemnt", "aemt", "aemtu", "aent", "aentu", "aet", "am", "amn", "amnt", "amntu", "amnu", "an", "ant", "antu", "atu", "em", "emn", "emnt", "emntu", "emnu", "emt", "emtu", "ent", "entu", "mtu", "mu", "tu"], "aemnrtv": ["aemnrtv", "aemn", "aemnr", "aemnrt", "aemnt", "aemnv", "aemr", "aemrt", "aemt", "aenr", "aenrt", "aenrtv", "aenrv", "aent", "aenv", "aer", "aert", "aertv", "aerv", "aet", "aev", "am", "amn", "amnrt", "amnt", "amr", "amrt", "an", "anrt", "anrv", "ant", "art", "artv", "arv", "em", "emn", "emnr", "emnrtv", "emnt", "emr", "emrt", "emt", "enr", "enrt", "enrtv", "enrv", "ent", "entv", "env", "ert", "ertv", "erv"], "aemnosw": ["aemnosw", "aemn", "aemno", "aemnos", "aemns", "aemnsw", "aemosw", "aems", "aemw", "aenos", "aens", "aensw", "aenw", "aeos", "aes", "aesw", "am", "amn", "amno", "amnos", "amnosw", "amnow", "amns", "amo", "amos", "ams", "amsw", "an", "ano", "anos", "ans", "answ", "anw", "as", "asw", "em", "emn", "emno", "emnos", "emnosw", "emnow", "emns", "emnsw", "emo", "emos", "emosw", "emow", "ems", "emsw", "eno", "enos", "enosw", "enow", "ens", "ensw", "enw", "eos", "eosw", "es", "esw", "mno", "mnos", "mos", "mosw", "no", "nos", "nosw", "osw"], "aemnx": ["aemnx", "aemn", "aemx", "aenx", "am", "amn", "an", "em", "emn"], "aemnpry": ["aemnpry", "aemn", "aemnp", "aemnr", "aemny", "aempr", "aempy", "aemr", "aemry", "aemy", "aenp", "aenpr", "aenpry", "aenr", "aenry", "aeny", "aepr", "aepry", "aepy", "aer", "aery", "am", "amn", "amnp", "amny", "amp", "ampr", "amr", "amry", "amy", "an", "anpr", "anpy", "anry", "any", "ap", "apr", "apry", "apy", "ary", "em", "emn", "emnp", "emnr", "emny", "empr", "empry", "emr", "emry", "enp", "enpr", "enpry", "enpy", "enr", "ep", "epr", "epry", "epy", "ery"], "aemnor": ["aemnor", "aemn", "aemno", "aemnr", "aemor", "aemr", "aenor", "aenr", "aeor", "aer", "am", "amn", "amno", "amnor", "amo", "amor", "amr", "an", "ano", "anor", "aor", "em", "emn", "emno", "emnor", "emnr", "emo", "emor", "emr", "eno", "enr", "eor", "mno", "mnor", "mor", "no"], "aemnors": ["aemnors", "aemn", "aemno", "aemnor", "aemnos", "aemnr", "aemnrs", "aemns", "aemor", "aemors", "aemr", "aemrs", "aems", "aenor", "aenors", "aenos", "aenr", "aenrs", "aens", "aeor", "aeors", "aeos", "aer", "aers", "aes", "am", "amn", "amno", "amnor", "amnors", "amnos", "amns", "amo", "amor", "amors", "amos", "amr", "amrs", "ams", "an", "ano", "anor", "anors", "anos", "anrs", "ans", "aor", "aors", "ars", "as", "em", "emn", "emno", "emnor", "emnors", "emnos", "emnr", "emns", "emo", "emor", "emors", "emos", "emr", "emrs", "ems", "eno", "enors", "enos", "enr", "enrs", "ens", "eor", "eors", "eos", "ers", "es", "mno", "mnor", "mnors", "mnos", "mor", "mors", "mos", "no", "nors", "nos"], "aemnrtu": ["aemnrtu", "aemn", "aemnr", "aemnrt", "aemnru", "aemnt", "aemntu", "aemr", "aemrt", "aemrtu", "aemru", "aemt", "aemtu", "aenr", "aenrt", "aenrtu", "aent", "aentu", "aer", "aert", "aertu", "aeru", "aet", "am", "amn", "amnrt", "amnrtu", "amnru", "amnt", "amntu", "amnu", "amr", "amrt", "amrtu", "amru", "an", "anrt", "anrtu", "anru", "ant", "antu", "art", "artu", "aru", "atu", "em", "emn", "emnr", "emnru", "emnt", "emntu", "emnu", "emr", "emrt", "emrtu", "emru", "emt", "emtu", "enr", "enrt", "enrtu", "enru", "ent", "entu", "ert", "ertu", "mru", "mtu", "mu", "nrtu", "tu"], "aemnrvy": ["aemnrvy", "aemn", "aemnr", "aemnv", "aemny", "aemr", "aemry", "aemy", "aenr", "aenrv", "aenry", "aenv", "aeny", "aer", "aerv", "aery", "aev", "am", "amn", "amny", "amr", "amry", "amy", "an", "anrv", "anry", "anvy", "any", "arv", "arvy", "ary", "em", "emn", "emnr", "emny", "emr", "emry", "enr", "enrv", "enrvy", "env", "envy", "erv", "ervy", "ery"], "aemnsx": ["aemnsx", "aemn", "aemns", "aemnx", "aems", "aemsx", "aemx", "aens", "aensx", "aenx", "aes", "aesx", "am", "amn", "amns", "ams", "an", "ans", "as", "em", "emn", "emns", "ems", "ens", "es", "esx"], "aemnruv": ["aemnruv", "aemn", "aemnr", "aemnru", "aemnv", "aemr", "aemru", "aemuv", "aenr", "aenrv", "aenuv", "aenv", "aer", "aeru", "aerv", "aeuv", "aev", "am", "amn", "amnru", "amnu", "amr", "amru", "an", "anru", "anrv", "aru", "arv", "em", "emn", "emnr", "emnru", "emnu", "emr", "emru", "enr", "enru", "enruv", "enrv", "enuv", "env", "eruv", "erv", "mru", "mu"], "aemnr": ["aemnr", "aemn", "aemr", "aenr", "aer", "am", "amn", "amr", "an", "em", "emn", "emnr", "emr", "enr"], "aemnrs": ["aemnrs", "aemn", "aemnr", "aemns", "aemr", "aemrs", "aems", "aenr", "aenrs", "aens", "aer", "aers", "aes", "am", "amn", "amns", "amr", "amrs", "ams", "an", "anrs", "ans", "ars", "as", "em", "emn", "emnr", "emns", "emr", "emrs", "ems", "enr", "enrs", "ens", "ers", "es"], "aemnqu": ["aemnqu", "aemn", "aenqu", "am", "amn", "amnu", "an", "aqu", "em", "emn", "emnu", "enqu", "equ", "mu"], "aemnopr": ["aemnopr", "aemn", "aemno", "aemnor", "aemnp", "aemnr", "aemopr", "aemor", "aempr", "aemr", "aenop", "aenopr", "aenor", "aenp", "aenpr", "aenr", "aeopr", "aeor", "aepr", "aer", "am", "amn", "amno", "amnop", "amnopr", "amnor", "amnp", "amo", "amopr", "amor", "amp", "ampr", "amr", "an", "ano", "anopr", "anor", "anpr", "aop", "aopr", "aor", "ap", "apr", "em", "emn", "emno", "emnopr", "emnor", "emnp", "emnr", "emo", "emop", "emopr", "emor", "empr", "emr", "eno", "enop", "enopr", "enp", "enpr", "enr", "eop", "eopr", "eor", "ep", "epr", "mno", "mnor", "mop", "mopr", "mor", "no", "nop", "nopr", "op", "opr"], "aemnru": ["aemnru", "aemn", "aemnr", "aemr", "aemru", "aenr", "aer", "aeru", "am", "amn", "amnru", "amnu", "amr", "amru", "an", "anru", "aru", "em", "emn", "emnr", "emnru", "emnu", "emr", "emru", "enr", "enru", "mru", "mu"], "aemnrsu": ["aemnrsu", "aemn", "aemnr", "aemnrs", "aemnru", "aemns", "aemnsu", "aemr", "aemrs", "aemrsu", "aemru", "aems", "aemsu", "aenr", "aenrs", "aens", "aensu", "aer", "aers", "aersu", "aeru", "aes", "am", "amn", "amnrsu", "amnru", "amns", "amnsu", "amnu", "amr", "amrs", "amrsu", "amru", "ams", "amsu", "an", "anrs", "anrsu", "anru", "ans", "ansu", "ars", "arsu", "aru", "as", "em", "emn", "emnr", "emnrsu", "emnru", "emns", "emnsu", "emnu", "emr", "emrs", "emrsu", "emru", "ems", "emsu", "enr", "enrs", "enrsu", "enru", "ens", "ensu", "ers", "ersu", "es", "esu", "mrsu", "mru", "msu", "mu", "nrsu", "nsu", "rsu", "su"], "aemnv": ["aemnv", "aemn", "aenv", "aev", "am", "amn", "an", "em", "emn", "env"], "aemnsv": ["aemnsv", "aemn", "aemns", "aemnv", "aems", "aens", "aensv", "aenv", "aes", "aesv", "aev", "am", "amn", "amns", "ams", "an", "ans", "ansv", "as", "asv", "em", "emn", "emns", "ems", "ens", "ensv", "env", "es", "esv"], "aemny": ["aemny", "aemn", "aemy", "aeny", "am", "amn", "amny", "amy", "an", "any", "em", "emn", "emny"], "aemnrsw": ["aemnrsw", "aemn", "aemnr", "aemnrs", "aemns", "aemnsw", "aemr", "aemrs", "aemrsw", "aemrw", "aems", "aemw", "aenr", "aenrs", "aenrsw", "aenrw", "aens", "aensw", "aenw", "aer", "aers", "aersw", "aerw", "aes", "aesw", "am", "amn", "amns", "amr", "amrs", "amrsw", "amrw", "ams", "amsw", "an", "anrs", "anrsw", "anrw", "ans", "answ", "anw", "ars", "arsw", "as", "asw", "em", "emn", "emnr", "emns", "emnsw", "emr", "emrs", "ems", "emsw", "enr", "enrs", "enrsw", "enrw", "ens", "ensw", "enw", "ers", "ersw", "erw", "es", "esw"], "aemnoru": ["aemnoru", "aemn", "aemno", "aemnor", "aemnou", "aemnr", "aemnru", "aemor", "aemr", "aemru", "aenor", "aenr", "aeor", "aer", "aeru", "am", "amn", "amno", "amnor", "amnru", "amnu", "amo", "amor", "amoru", "amr", "amru", "an", "ano", "anor", "anru", "aor", "aoru", "aru", "em", "emn", "emno", "emnor", "emnoru", "emnou", "emnr", "emnru", "emnu", "emo", "emor", "emou", "emr", "emru", "eno", "enoru", "enr", "enru", "eor", "eoru", "mno", "mnor", "mnoru", "mnou", "mor", "moru", "mru", "mu", "no", "nou"], "aemnsw": ["aemnsw", "aemn", "aemns", "aems", "aemw", "aens", "aensw", "aenw", "aes", "aesw", "am", "amn", "amns", "ams", "amsw", "an", "ans", "answ", "anw", "as", "asw", "em", "emn", "emns", "emnsw", "ems", "emsw", "ens", "ensw", "enw", "es", "esw"], "aemnou": ["aemnou", "aemn", "aemno", "am", "amn", "amno", "amnu", "amo", "an", "ano", "em", "emn", "emno", "emnou", "emnu", "emo", "emou", "eno", "mno", "mnou", "mu", "no", "nou"], "aemnruy": ["aemnruy", "aemn", "aemnr", "aemnru", "aemny", "aemr", "aemru", "aemry", "aemy", "aenr", "aenry", "aeny", "aer", "aeru", "aery", "am", "amn", "amnru", "amnruy", "amnu", "amny", "amr", "amru", "amry", "amy", "an", "anru", "anruy", "anry", "anuy", "any", "aru", "ary", "em", "emn", "emnr", "emnru", "emnu", "emny", "emr", "emru", "emruy", "emry", "enr", "enru", "enruy", "ery", "mru", "mruy", "mu", "muy", "nruy"], "aemnorv": ["aemnorv", "aemn", "aemno", "aemnor", "aemnr", "aemnv", "aemor", "aemorv", "aemr", "aenor", "aenorv", "aenov", "aenr", "aenrv", "aenv", "aeor", "aer", "aerv", "aev", "am", "amn", "amno", "amnor", "amo", "amor", "amr", "an", "ano", "anor", "anov", "anrv", "aor", "aorv", "arv", "em", "emn", "emno", "emnor", "emnorv", "emnov", "emnr", "emo", "emor", "emorv", "emov", "emr", "eno", "enov", "enr", "enrv", "env", "eor", "eorv", "erv", "mno", "mnor", "mor", "no"], "aemnptv": ["aemnptv", "aemn", "aemnp", "aemnt", "aemnv", "aempt", "aemt", "aenp", "aenpt", "aenpv", "aent", "aenv", "aept", "aepv", "aet", "aev", "am", "amn", "amnp", "amnt", "amp", "ampt", "ampv", "an", "anpt", "anpv", "ant", "ap", "em", "emn", "emnp", "emnt", "empt", "emt", "enp", "enpt", "ent", "entv", "env", "ep", "ept", "epv"], "aemnpty": ["aemnpty", "aemn", "aemnp", "aemnt", "aemny", "aempt", "aempy", "aemt", "aemty", "aemy", "aenp", "aenpt", "aenpty", "aent", "aenty", "aeny", "aept", "aepty", "aepy", "aet", "am", "amn", "amnp", "amnpty", "amnt", "amny", "amp", "ampt", "amty", "amy", "an", "anpt", "anpy", "ant", "anty", "any", "ap", "apty", "apy", "aty", "em", "emn", "emnp", "emnt", "emny", "empt", "empty", "emt", "enp", "enpt", "enpty", "enpy", "ent", "enty", "ep", "ept", "epty", "epy"], "aemnpu": ["aemnpu", "aemn", "aemnp", "aenp", "aepu", "am", "amn", "amnp", "amnu", "amp", "ampu", "an", "ap", "apu", "em", "emn", "emnp", "emnu", "enp", "enpu", "ep", "mpu", "mu"], "aemnprs": ["aemnprs", "aemn", "aemnp", "aemnr", "aemnrs", "aemns", "aempr", "aemprs", "aemr", "aemrs", "aems", "aenp", "aenpr", "aenprs", "aenps", "aenr", "aenrs", "aens", "aepr", "aeprs", "aeps", "aer", "aers", "aes", "am", "amn", "amnp", "amnps", "amns", "amp", "ampr", "amprs", "amps", "amr", "amrs", "ams", "an", "anpr", "anps", "anrs", "ans", "ap", "apr", "aprs", "aps", "ars", "as", "em", "emn", "emnp", "emnprs", "emnr", "emns", "empr", "emprs", "emr", "emrs", "ems", "enp", "enpr", "enprs", "enps", "enr", "enrs", "ens", "ep", "epr", "eprs", "eps", "ers", "es"], "aemnptu": ["aemnptu", "aemn", "aemnp", "aemnpu", "aemnt", "aemntu", "aempt", "aemptu", "aemt", "aemtu", "aenp", "aenpt", "aenptu", "aent", "aentu", "aept", "aeptu", "aepu", "aet", "am", "amn", "amnp", "amnt", "amntu", "amnu", "amp", "ampt", "ampu", "an", "anpt", "anptu", "ant", "antu", "ap", "apu", "atu", "em", "emn", "emnp", "emnptu", "emnt", "emntu", "emnu", "empt", "emptu", "emt", "emtu", "enp", "enpt", "enptu", "enpu", "ent", "entu", "ep", "ept", "eptu", "mpu", "mtu", "mu", "nptu", "ptu", "tu"], "aemntx": ["aemntx", "aemn", "aemnt", "aemnx", "aemt", "aemtx", "aemx", "aent", "aentx", "aenx", "aet", "aetx", "am", "amn", "amnt", "amntx", "an", "ant", "atx", "em", "emn", "emnt", "emt", "ent", "entx", "etx"], "aemnrtw": ["aemnrtw", "aemn", "aemnr", "aemnrt", "aemnt", "aemr", "aemrt", "aemrtw", "aemrw", "aemt", "aemw", "aenr", "aenrt", "aenrtw", "aenrw", "aent", "aentw", "aenw", "aer", "aert", "aertw", "aerw", "aet", "am", "amn", "amnrt", "amnt", "amr", "amrt", "amrw", "an", "anrt", "anrtw", "anrw", "ant", "antw", "anw", "art", "artw", "atw", "em", "emn", "emnr", "emnt", "emr", "emrt", "emt", "enr", "enrt", "enrw", "ent", "entw", "enw", "ert", "ertw", "erw", "etw"], "aemnoy": ["aemnoy", "aemn", "aemno", "aemny", "aemy", "aenoy", "aeny", "am", "amn", "amno", "amnoy", "amny", "amo", "amoy", "amy", "an", "ano", "anoy", "any", "em", "emn", "emno", "emnoy", "emny", "emo", "eno", "mno", "mnoy", "moy", "no"]}