{"agirst": ["agirst", "ag", "agir", "agirs", "agis", "agist", "agit", "agr", "agrs", "agrst", "agrt", "ags", "agst", "air", "airs", "airst", "airt", "ais", "aist", "ars", "arst", "art", "as", "ast", "gir", "girs", "girst", "girt", "gis", "gist", "irs", "irst", "ist", "it"], "agirtuy": ["agirtuy", "ag", "agir", "agirtu", "agit", "agr", "agrt", "agrtu", "agru", "agruy", "agry", "agtu", "air", "airt", "airty", "airy", "aituy", "art", "artu", "arty", "aru", "ary", "atu", "aty", "gir", "girt", "girty", "grtu", "gru", "gtuy", "it", "itu", "ity", "rtuy", "tu", "tuy"], "agirstv": ["agirstv", "ag", "agir", "agirs", "agirst", "agirsv", "agirv", "agis", "agist", "agit", "agiv", "agr", "agrs", "agrst", "agrt", "ags", "agst", "air", "airs", "airst", "airstv", "airt", "airtv", "airv", "ais", "aist", "aistv", "aisv", "aitv", "aiv", "ars", "arst", "arstv", "arsv", "art", "artv", "arv", "as", "ast", "astv", "asv", "gir", "girs", "girst", "girt", "gis", "gist", "irs", "irst", "ist", "istv", "it", "iv"], "agirtvy": ["agirtvy", "ag", "agir", "agirv", "agit", "agiv", "agr", "agrt", "agrvy", "agry", "air", "airt", "airtv", "airty", "airv", "airvy", "airy", "aitv", "aiv", "art", "artv", "arty", "arv", "arvy", "ary", "aty", "gir", "girt", "girty", "it", "ity", "iv"], "agirtu": ["agirtu", "ag", "agir", "agit", "agr", "agrt", "agrtu", "agru", "agtu", "air", "airt", "art", "artu", "aru", "atu", "gir", "girt", "grtu", "gru", "it", "itu", "tu"], "agirstu": ["agirstu", "ag", "agir", "agirs", "agirst", "agirtu", "agis", "agist", "agit", "agr", "agrs", "agrst", "agrstu", "agrsu", "agrt", "agrtu", "agru", "ags", "agst", "agstu", "agsu", "agtu", "air", "airs", "airst", "airstu", "airt", "ais", "aist", "ars", "arst", "arstu", "arsu", "art", "artu", "aru", "as", "ast", "astu", "atu", "gir", "girs", "girst", "girt", "gis", "gist", "grstu", "grsu", "grtu", "gru", "gstu", "irs", "irst", "irstu", "ist", "istu", "it", "itu", "rstu", "rsu", "stu", "su", "tu"], "agir": ["agir", "ag", "agr", "air", "gir"], "agirs": ["agirs", "ag", "agir", "agis", "agr", "agrs", "ags", "air", "airs", "ais", "ars", "as", "gir", "girs", "gis", "irs"], "agirv": ["agirv", "ag", "agir", "agiv", "agr", "air", "airv", "aiv", "arv", "gir", "iv"], "agirsv": ["agirsv", "ag", "agir", "agirs", "agirv", "agis", "agiv", "agr", "agrs", "ags", "air", "airs", "airv", "ais", "aisv", "aiv", "ars", "arsv", "arv", "as", "asv", "gir", "girs", "gis", "irs", "iv"], "agirtuz": ["agirtuz", "ag", "agir", "agirtu", "agit", "agiz", "agr", "agrt", "agrtu", "agru", "agtu", "air", "airt", "airz", "art", "artu", "aru", "arz", "atu", "atz", "gir", "girt", "grtu", "gru", "it", "itu", "itz", "tu"]}