{"aimnr": ["aimnr", "aim", "aimn", "aimr", "ainr", "air", "am", "amn", "amr", "an", "imn", "imnr"], "aimnorw": ["aimnorw", "aim", "aimn", "aimno", "aimnor", "aimnr", "aimr", "aino", "ainor", "ainr", "ainw", "aiorw", "air", "airw", "am", "amn", "amno", "amnor", "amnow", "amo", "amor", "amorw", "amr", "amrw", "an", "ano", "anor", "anorw", "anrw", "anw", "aor", "aorw", "imn", "imno", "imnor", "imnow", "imnr", "imor", "ino", "inor", "inow", "mno", "mnor", "mor", "morw", "no", "norw"], "aimn": ["aimn", "aim", "am", "amn", "an", "imn"], "aimnt": ["aimnt", "aim", "aimn", "aimt", "aint", "am", "amn", "amnt", "an", "ant", "imn", "imnt", "imt", "int", "it"], "aimnoz": ["aimnoz", "aim", "aimn", "aimno", "aimz", "aino", "ainz", "am", "amn", "amno", "amnoz", "amo", "an", "ano", "anz", "imn", "imno", "ino", "mno", "moz", "no", "noz"], "aimno": ["aimno", "aim", "aimn", "aino", "am", "amn", "amno", "amo", "an", "ano", "imn", "imno", "ino", "mno", "no"], "aimnou": ["aimnou", "aim", "aimn", "aimno", "aimnu", "aino", "am", "amn", "amno", "amnu", "amo", "an", "ano", "imn", "imno", "imnou", "imnu", "ino", "inou", "mno", "mnou", "mu", "no", "nou"], "aimnosu": ["aimnosu", "aim", "aimn", "aimno", "aimnos", "aimnou", "aimns", "aimnsu", "aimnu", "aimos", "aims", "aino", "ainos", "ainosu", "ains", "aios", "ais", "am", "amn", "amno", "amnos", "amns", "amnsu", "amnu", "amo", "amos", "amosu", "ams", "amsu", "an", "ano", "anos", "ans", "ansu", "as", "imn", "imno", "imnos", "imnosu", "imnou", "imns", "imnsu", "imnu", "imos", "imosu", "ims", "imsu", "ino", "inos", "inosu", "inou", "ins", "insu", "mno", "mnos", "mnosu", "mnou", "mos", "mosu", "msu", "mu", "no", "nos", "nosu", "nou", "nsu", "osu", "su"], "aimnotu": ["aimnotu", "aim", "aimn", "aimno", "aimnot", "aimnou", "aimnt", "aimntu", "aimnu", "aimt", "aino", "ainot", "ainotu", "aint", "aintu", "aiot", "am", "amn", "amno", "amnot", "amnotu", "amnt", "amntu", "amnu", "amo", "amot", "amotu", "an", "ano", "anot", "ant", "antu", "aot", "aotu", "atu", "imn", "imno", "imnot", "imnotu", "imnou", "imnt", "imntu", "imnu", "imot", "imt", "ino", "inot", "inotu", "inou", "int", "intu", "it", "itu", "mno", "mnotu", "mnou", "mot", "mtu", "mu", "no", "not", "notu", "nou", "ot", "otu", "tu"], "aimnos": ["aimnos", "aim", "aimn", "aimno", "aimns", "aimos", "aims", "aino", "ainos", "ains", "aios", "ais", "am", "amn", "amno", "amnos", "amns", "amo", "amos", "ams", "an", "ano", "anos", "ans", "as", "imn", "imno", "imnos", "imns", "imos", "ims", "ino", "inos", "ins", "mno", "mnos", "mos", "no", "nos"], "aimnor": ["aimnor", "aim", "aimn", "aimno", "aimnr", "aimr", "aino", "ainor", "ainr", "air", "am", "amn", "amno", "amnor", "amo", "amor", "amr", "an", "ano", "anor", "aor", "imn", "imno", "imnor", "imnr", "imor", "ino", "inor", "mno", "mnor", "mor", "no"], "aimnoty": ["aimnoty", "aim", "aimn", "aimno", "aimnot", "aimnt", "aimny", "aimt", "aimty", "aino", "ainot", "aint", "ainty", "ainy", "aiot", "am", "amn", "amno", "amnot", "amnoty", "amnoy", "amnt", "amny", "amo", "amot", "amoty", "amoy", "amty", "amy", "an", "ano", "anot", "anoty", "anoy", "ant", "anty", "any", "aot", "aty", "imn", "imno", "imnot", "imnt", "imnty", "imot", "imt", "ino", "inot", "inoy", "int", "inty", "iny", "it", "ity", "mno", "mnoty", "mnoy", "mot", "moy", "no", "not", "noty", "ot"], "aimnost": ["aimnost", "aim", "aimn", "aimno", "aimnos", "aimnot", "aimns", "aimnst", "aimnt", "aimos", "aimost", "aims", "aimst", "aimt", "aino", "ainos", "ainost", "ainot", "ains", "ainst", "aint", "aios", "aiost", "aiot", "ais", "aist", "am", "amn", "amno", "amnos", "amnost", "amnot", "amns", "amnst", "amnt", "amo", "amos", "amost", "amot", "ams", "amst", "an", "ano", "anos", "anost", "anot", "ans", "anst", "ant", "aost", "aot", "as", "ast", "imn", "imno", "imnos", "imnost", "imnot", "imns", "imnst", "imnt", "imos", "imost", "imot", "ims", "imst", "imt", "ino", "inos", "inost", "inot", "ins", "inst", "int", "iost", "ist", "it", "mno", "mnos", "mos", "most", "mot", "no", "nos", "nost", "not", "ost", "ot"], "aimns": ["aimns", "aim", "aimn", "aims", "ains", "ais", "am", "amn", "amns", "ams", "an", "ans", "as", "imn", "imns", "ims", "ins"], "aimnot": ["aimnot", "aim", "aimn", "aimno", "aimnt", "aimt", "aino", "ainot", "aint", "aiot", "am", "amn", "amno", "amnot", "amnt", "amo", "amot", "an", "ano", "anot", "ant", "aot", "imn", "imno", "imnot", "imnt", "imot", "imt", "ino", "inot", "int", "it", "mno", "mot", "no", "not", "ot"], "aimnst": ["aimnst", "aim", "aimn", "aimns", "aimnt", "aims", "aimst", "aimt", "ains", "ainst", "aint", "ais", "aist", "am", "amn", "amns", "amnst", "amnt", "ams", "amst", "an", "ans", "anst", "ant", "as", "ast", "imn", "imns", "imnst", "imnt", "ims", "imst", "imt", "ins", "inst", "int", "ist", "it"], "aimnort": ["aimnort", "aim", "aimn", "aimno", "aimnor", "aimnot", "aimnr", "aimnrt", "aimnt", "aimort", "aimr", "aimrt", "aimt", "aino", "ainor", "ainort", "ainot", "ainr", "ainrt", "aint", "aiort", "aiot", "air", "airt", "am", "amn", "amno", "amnor", "amnort", "amnot", "amnrt", "amnt", "amo", "amor", "amort", "amot", "amr", "amrt", "an", "ano", "anor", "anort", "anot", "anrt", "ant", "aor", "aort", "aot", "art", "imn", "imno", "imnor", "imnort", "imnot", "imnr", "imnt", "imor", "imot", "imrt", "imt", "ino", "inor", "inort", "inot", "inrt", "int", "iort", "it", "mno", "mnor", "mor", "mort", "mot", "no", "nort", "not", "ort", "ot"], "aimnsu": ["aimnsu", "aim", "aimn", "aimns", "aimnu", "aims", "ains", "ais", "am", "amn", "amns", "amnsu", "amnu", "ams", "amsu", "an", "ans", "ansu", "as", "imn", "imns", "imnsu", "imnu", "ims", "imsu", "ins", "insu", "msu", "mu", "nsu", "su"], "aimnotz": ["aimnotz", "aim", "aimn", "aimno", "aimnot", "aimnoz", "aimnt", "aimntz", "aimt", "aimz", "aino", "ainot", "ainotz", "aint", "ainz", "aiot", "am", "amn", "amno", "amnot", "amnoz", "amnt", "amo", "amot", "amotz", "an", "ano", "anot", "ant", "anz", "aot", "atz", "imn", "imno", "imnot", "imnt", "imot", "imt", "ino", "inot", "int", "it", "itz", "mno", "mot", "moz", "no", "not", "noz", "ot"], "aimnopt": ["aimnopt", "aim", "aimn", "aimno", "aimnot", "aimnpt", "aimnt", "aimopt", "aimt", "aino", "ainop", "ainopt", "ainot", "ainp", "ainpt", "aint", "aiopt", "aiot", "aipt", "am", "amn", "amno", "amnop", "amnopt", "amnot", "amnp", "amnt", "amo", "amot", "amp", "ampt", "an", "ano", "anopt", "anot", "anpt", "ant", "aop", "aopt", "aot", "ap", "imn", "imno", "imnopt", "imnot", "imnt", "imot", "imp", "imt", "ino", "inop", "inopt", "inot", "inp", "inpt", "int", "iopt", "ipt", "it", "mno", "mop", "mot", "no", "nop", "nopt", "not", "op", "opt", "ot"], "aimnops": ["aimnops", "aim", "aimn", "aimno", "aimnos", "aimnps", "aimns", "aimos", "aimps", "aims", "aino", "ainop", "ainops", "ainos", "ainp", "ainps", "ains", "aios", "aips", "ais", "am", "amn", "amno", "amnop", "amnops", "amnos", "amnp", "amnps", "amns", "amo", "amos", "amp", "amps", "ams", "an", "ano", "anos", "anps", "ans", "aop", "aops", "ap", "aps", "as", "imn", "imno", "imnos", "imns", "imos", "imp", "imps", "ims", "ino", "inop", "inops", "inos", "inp", "inps", "ins", "iops", "ips", "mno", "mnos", "mop", "mops", "mos", "no", "nop", "nops", "nos", "op", "ops"], "aimnsty": ["aimnsty", "aim", "aimn", "aimns", "aimnst", "aimnt", "aimny", "aims", "aimst", "aimsy", "aimt", "aimty", "ains", "ainst", "ainsty", "ainsy", "aint", "ainty", "ainy", "ais", "aist", "am", "amn", "amns", "amnst", "amnsy", "amnt", "amny", "ams", "amst", "amsty", "amsy", "amty", "amy", "an", "ans", "anst", "ansty", "ansy", "ant", "anty", "any", "as", "ast", "asty", "asy", "aty", "imn", "imns", "imnst", "imnt", "imnty", "ims", "imst", "imsty", "imsy", "imt", "ins", "inst", "int", "inty", "iny", "ist", "isy", "it", "ity", "sty"], "aimntu": ["aimntu", "aim", "aimn", "aimnt", "aimnu", "aimt", "aint", "aintu", "am", "amn", "amnt", "amntu", "amnu", "an", "ant", "antu", "atu", "imn", "imnt", "imntu", "imnu", "imt", "int", "intu", "it", "itu", "mtu", "mu", "tu"], "aimnstu": ["aimnstu", "aim", "aimn", "aimns", "aimnst", "aimnsu", "aimnt", "aimntu", "aimnu", "aims", "aimst", "aimstu", "aimt", "ains", "ainst", "ainstu", "aint", "aintu", "ais", "aist", "am", "amn", "amns", "amnst", "amnstu", "amnsu", "amnt", "amntu", "amnu", "ams", "amst", "amstu", "amsu", "an", "ans", "anst", "anstu", "ansu", "ant", "antu", "as", "ast", "astu", "atu", "imn", "imns", "imnst", "imnsu", "imnt", "imntu", "imnu", "ims", "imst", "imstu", "imsu", "imt", "ins", "inst", "instu", "insu", "int", "intu", "ist", "istu", "it", "itu", "mstu", "msu", "mtu", "mu", "nstu", "nsu", "stu", "su", "tu"], "aimntz": ["aimntz", "aim", "aimn", "aimnt", "aimt", "aimz", "aint", "ainz", "am", "amn", "amnt", "an", "ant", "anz", "atz", "imn", "imnt", "imt", "int", "it", "itz"], "aimnstz": ["aimnstz", "aim", "aimn", "aimns", "aimnst", "aimnt", "aimntz", "aims", "aimst", "aimsz", "aimt", "aimz", "ains", "ainst", "ainsz", "aint", "ainz", "ais", "aist", "am", "amn", "amns", "amnst", "amnt", "ams", "amst", "an", "ans", "anst", "anstz", "ant", "anz", "as", "ast", "atz", "imn", "imns", "imnst", "imnt", "ims", "imst", "imt", "ins", "inst", "int", "ist", "istz", "it", "itz"], "aimnrs": ["aimnrs", "aim", "aimn", "aimnr", "aimns", "aimr", "aimrs", "aims", "ainr", "ainrs", "ains", "air", "airs", "ais", "am", "amn", "amns", "amr", "amrs", "ams", "an", "anrs", "ans", "ars", "as", "imn", "imnr", "imns", "imrs", "ims", "ins", "irs"], "aimnrt": ["aimnrt", "aim", "aimn", "aimnr", "aimnt", "aimr", "aimrt", "aimt", "ainr", "ainrt", "aint", "air", "airt", "am", "amn", "amnrt", "amnt", "amr", "amrt", "an", "anrt", "ant", "art", "imn", "imnr", "imnt", "imrt", "imt", "inrt", "int", "it"], "aimnrst": ["aimnrst", "aim", "aimn", "aimnr", "aimnrs", "aimnrt", "aimns", "aimnst", "aimnt", "aimr", "aimrs", "aimrst", "aimrt", "aims", "aimst", "aimt", "ainr", "ainrs", "ainrst", "ainrt", "ains", "ainst", "aint", "air", "airs", "airst", "airt", "ais", "aist", "am", "amn", "amnrst", "amnrt", "amns", "amnst", "amnt", "amr", "amrs", "amrst", "amrt", "ams", "amst", "an", "anrs", "anrst", "anrt", "ans", "anst", "ant", "ars", "arst", "art", "as", "ast", "imn", "imnr", "imns", "imnst", "imnt", "imrs", "imrst", "imrt", "ims", "imst", "imt", "inrst", "inrt", "ins", "inst", "int", "irs", "irst", "ist", "it"], "aimnprz": ["aimnprz", "aim", "aimn", "aimnr", "aimpr", "aimr", "aimrz", "aimz", "ainp", "ainpr", "ainr", "ainz", "aipr", "aiprz", "aipz", "air", "airz", "am", "amn", "amnp", "amp", "ampr", "amr", "an", "anpr", "anz", "ap", "apr", "apz", "arz", "imn", "imnr", "imp", "impr", "inp", "inpr", "ipz"], "aimnx": ["aimnx", "aim", "aimn", "aimx", "aix", "am", "amn", "an", "imn", "imnx", "imx", "ix"], "aimnv": ["aimnv", "aim", "aimn", "ainv", "aiv", "am", "amn", "an", "imn", "iv"], "aimnsv": ["aimnsv", "aim", "aimn", "aimns", "aimnv", "aims", "aimsv", "ains", "ainv", "ais", "aisv", "aiv", "am", "amn", "amns", "ams", "an", "ans", "ansv", "as", "asv", "imn", "imns", "ims", "ins", "iv"], "aimny": ["aimny", "aim", "aimn", "ainy", "am", "amn", "amny", "amy", "an", "any", "imn", "iny"], "aimnotv": ["aimnotv", "aim", "aimn", "aimno", "aimnot", "aimnt", "aimntv", "aimnv", "aimt", "aino", "ainot", "ainotv", "ainov", "aint", "ainv", "aiot", "aitv", "aiv", "am", "amn", "amno", "amnot", "amnt", "amo", "amot", "an", "ano", "anot", "anov", "ant", "aot", "aotv", "imn", "imno", "imnot", "imnt", "imot", "imotv", "imt", "ino", "inot", "inov", "int", "intv", "it", "iv", "mno", "mot", "no", "not", "ot"], "aimnru": ["aimnru", "aim", "aimn", "aimnr", "aimnu", "aimr", "ainr", "ainru", "air", "am", "amn", "amnru", "amnu", "amr", "amru", "an", "anru", "aru", "imn", "imnr", "imnu", "inru", "mru", "mu"], "aimnstv": ["aimnstv", "aim", "aimn", "aimns", "aimnst", "aimnsv", "aimnt", "aimntv", "aimnv", "aims", "aimst", "aimstv", "aimsv", "aimt", "ains", "ainst", "ainstv", "aint", "ainv", "ais", "aist", "aistv", "aisv", "aitv", "aiv", "am", "amn", "amns", "amnst", "amnt", "ams", "amst", "an", "ans", "anst", "anstv", "ansv", "ant", "as", "ast", "astv", "asv", "imn", "imns", "imnst", "imnt", "ims", "imst", "imt", "ins", "inst", "int", "intv", "ist", "istv", "it", "iv"], "aimnu": ["aimnu", "aim", "aimn", "am", "amn", "amnu", "an", "imn", "imnu", "mu"], "aimnpy": ["aimnpy", "aim", "aimn", "aimny", "ainp", "ainy", "am", "amn", "amnp", "amny", "amp", "amy", "an", "anpy", "any", "ap", "apy", "imn", "imp", "inp", "inpy", "iny"], "aimnpsy": ["aimnpsy", "aim", "aimn", "aimnps", "aimnpy", "aimns", "aimny", "aimps", "aims", "aimsy", "ainp", "ainps", "ainpsy", "ains", "ainsy", "ainy", "aips", "ais", "am", "amn", "amnp", "amnps", "amns", "amnsy", "amny", "amp", "amps", "ams", "amsy", "amy", "an", "anps", "anpsy", "anpy", "ans", "ansy", "any", "ap", "aps", "apsy", "apy", "as", "asy", "imn", "imns", "imp", "imps", "ims", "imsy", "inp", "inps", "inpsy", "inpy", "ins", "iny", "ips", "ipsy", "isy"], "aimnps": ["aimnps", "aim", "aimn", "aimns", "aimps", "aims", "ainp", "ainps", "ains", "aips", "ais", "am", "amn", "amnp", "amnps", "amns", "amp", "amps", "ams", "an", "anps", "ans", "ap", "aps", "as", "imn", "imns", "imp", "imps", "ims", "inp", "inps", "ins", "ips"], "aimnpt": ["aimnpt", "aim", "aimn", "aimnt", "aimt", "ainp", "ainpt", "aint", "aipt", "am", "amn", "amnp", "amnt", "amp", "ampt", "an", "anpt", "ant", "ap", "imn", "imnt", "imp", "imt", "inp", "inpt", "int", "ipt", "it"], "aimnpst": ["aimnpst", "aim", "aimn", "aimnps", "aimnpt", "aimns", "aimnst", "aimnt", "aimps", "aims", "aimst", "aimt", "ainp", "ainps", "ainpst", "ainpt", "ains", "ainst", "aint", "aips", "aipst", "aipt", "ais", "aist", "am", "amn", "amnp", "amnps", "amns", "amnst", "amnt", "amp", "amps", "ampst", "ampt", "ams", "amst", "an", "anps", "anpst", "anpt", "ans", "anst", "ant", "ap", "aps", "apst", "as", "ast", "imn", "imns", "imnst", "imnt", "imp", "imps", "ims", "imst", "imt", "inp", "inps", "inpst", "inpt", "ins", "inst", "int", "ips", "ipst", "ipt", "ist", "it", "pst"], "aimnrtu": ["aimnrtu", "aim", "aimn", "aimnr", "aimnrt", "aimnru", "aimnt", "aimntu", "aimnu", "aimr", "aimrt", "aimrtu", "aimt", "ainr", "ainrt", "ainrtu", "ainru", "aint", "aintu", "air", "airt", "am", "amn", "amnrt", "amnrtu", "amnru", "amnt", "amntu", "amnu", "amr", "amrt", "amrtu", "amru", "an", "anrt", "anrtu", "anru", "ant", "antu", "art", "artu", "aru", "atu", "imn", "imnr", "imnt", "imntu", "imnu", "imrt", "imrtu", "imt", "inrt", "inru", "int", "intu", "it", "itu", "mru", "mtu", "mu", "nrtu", "tu"], "aimnpty": ["aimnpty", "aim", "aimn", "aimnpt", "aimnpy", "aimnt", "aimny", "aimt", "aimty", "ainp", "ainpt", "ainpty", "aint", "ainty", "ainy", "aipt", "am", "amn", "amnp", "amnpty", "amnt", "amny", "amp", "ampt", "amty", "amy", "an", "anpt", "anpy", "ant", "anty", "any", "ap", "apty", "apy", "aty", "imn", "imnt", "imnty", "imp", "imt", "inp", "inpt", "inpy", "int", "inty", "iny", "ipt", "ipty", "it", "ity"], "aimntuy": ["aimntuy", "aim", "aimn", "aimnt", "aimntu", "aimnu", "aimny", "aimt", "aimty", "aint", "aintu", "aintuy", "ainty", "ainy", "aituy", "am", "amn", "amnt", "amntu", "amnu", "amny", "amty", "amy", "an", "ant", "antu", "anty", "anuy", "any", "atu", "aty", "imn", "imnt", "imntu", "imntuy", "imnty", "imnu", "imt", "int", "intu", "intuy", "inty", "iny", "it", "itu", "ity", "mtu", "mtuy", "mu", "muy", "ntuy", "tu", "tuy"], "aimnrtv": ["aimnrtv", "aim", "aimn", "aimnr", "aimnrt", "aimnt", "aimntv", "aimnv", "aimr", "aimrt", "aimt", "ainr", "ainrt", "ainrtv", "ainrv", "aint", "ainv", "air", "airt", "airtv", "airv", "aitv", "aiv", "am", "amn", "amnrt", "amnt", "amr", "amrt", "an", "anrt", "anrv", "ant", "art", "artv", "arv", "imn", "imnr", "imnt", "imrt", "imt", "inrt", "int", "intv", "it", "iv"], "aimntv": ["aimntv", "aim", "aimn", "aimnt", "aimnv", "aimt", "aint", "ainv", "aitv", "aiv", "am", "amn", "amnt", "an", "ant", "imn", "imnt", "imt", "int", "intv", "it", "iv"]}