{"anort": ["anort", "anor"], "anorst": ["anorst", "anor", "anors", "anort"], "anorsu": ["anorsu", "anor", "anors"], "anors": ["anors", "anor"], "anorstu": ["anorstu", "anor", "anors", "anorst", "anorsu", "anort", "anortu"], "anorw": ["anorw", "anor"], "anorsw": ["anorsw", "anor", "anors", "anorw"], "anorty": ["anorty", "anor", "anort", "anory"], "anory": ["anory", "anor"], "anortu": ["anortu", "anor", "anort"], "anor": ["anor"], "anorsty": ["anorsty", "anor", "anors", "anorst", "anorsy", "anort", "anorty", "anory"], "anorsy": ["anorsy", "anor", "anors", "anory"], "anorsv": ["anorsv", "anor", "anors"], "anortw": ["anortw", "anor", "anort", "anorw"], "anorstw": ["anorstw", "anor", "anors", "anorst", "anorsw", "anort", "anortw", "anorw"], "anorwy": ["anorwy", "anor", "anorw", "anory"]}