{"bfilmo": ["bfilmo", "bfi", "bfo", "bi", "bil", "bilm", "bilmo", "bilo", "bimo", "blmo", "blo", "bmo", "bo", "fil", "film", "filo", "fim", "flo", "ilm", "ilmo", "ilo", "lmo", "lo"], "bfilmos": ["bfilmos", "bfi", "bfilmo", "bfis", "bfo", "bfos", "bi", "bil", "bilm", "bilmo", "bilmos", "bilms", "bilo", "bilos", "bils", "bimo", "bimos", "bios", "bis", "blmo", "blmos", "blo", "blos", "bmo", "bmos", "bo", "bos", "fil", "film", "films", "filo", "filos", "fils", "fim", "fims", "flo", "flos", "fos", "ilm", "ilmo", "ilmos", "ilms", "ilo", "ilos", "ils", "imos", "ims", "lmo", "lmos", "lo", "los", "mos"], "bfilsu": ["bfilsu", "bfi", "bfis", "bflsu", "bflu", "bfsu", "bfu", "bi", "bil", "bils", "bilsu", "bilu", "bis", "blsu", "blu", "bsu", "fil", "fils", "filsu", "filu", "flsu", "flu", "fsu", "ils", "ilsu", "lsu", "lu", "su"], "bfilsuy": ["bfilsuy", "bfi", "bfilsu", "bfis", "bflsu", "bflsy", "bflu", "bfluy", "bfly", "bfsu", "bfsuy", "bfu", "bi", "bil", "bils", "bilsu", "bilsuy", "bilsy", "bilu", "bily", "bis", "blsu", "blu", "bluy", "bsu", "bsuy", "fil", "fils", "filsu", "filsuy", "filu", "filuy", "fily", "fiy", "flsu", "flu", "fluy", "fsu", "fsuy", "ils", "ilsu", "ilsy", "ily", "isy", "lsu", "lsuy", "lsy", "lu", "su"], "bfilmru": ["bfilmru", "bfi", "bfilr", "bflu", "bfmu", "bfu", "bi", "bil", "bilm", "bilr", "bilu", "bimr", "bir", "blru", "blu", "bru", "fil", "film", "filmu", "filr", "filu", "fim", "fimr", "fir", "flru", "flu", "fmu", "fru", "ilm", "ilmu", "ilr", "lmu", "lu", "mru", "mu"], "bfilr": ["bfilr", "bfi", "bi", "bil", "bilr", "bir", "fil", "filr", "fir", "ilr"], "bfilmor": ["bfilmor", "bfi", "bfilmo", "bfilr", "bfimor", "bfmor", "bfo", "bfor", "bi", "bil", "bilm", "bilmo", "bilmor", "bilo", "bilor", "bilr", "bimo", "bimr", "bior", "bir", "blmo", "blo", "bmo", "bmor", "bo", "bor", "fil", "film", "filmor", "filo", "filr", "fim", "fimr", "fir", "flo", "flor", "fmor", "for", "ilm", "ilmo", "ilo", "ilor", "ilr", "imor", "lmo", "lo", "lor", "mor"], "bfilrs": ["bfilrs", "bfi", "bfilr", "bfis", "bi", "bil", "bilr", "bilrs", "bils", "bir", "birs", "bis", "fil", "filr", "filrs", "fils", "fir", "firs", "ilr", "ilrs", "ils", "irs"]}