{"bgin": ["bgin", "bi", "gin"], "bgins": ["bgins", "bgin", "bi", "bins", "bis", "gin", "gins", "gis", "ins"], "bgino": ["bgino", "bgin", "bgio", "bgno", "bgo", "bi", "bino", "bno", "bo", "gin", "gino", "gno", "ino", "no"], "bginr": ["bginr", "bgin", "bgir", "bi", "bir", "gin", "ginr", "gir"], "bgint": ["bgint", "bgin", "bi", "bit", "gin", "gint", "int", "it"], "bginost": ["bginost", "bgin", "bgino", "bginos", "bginot", "bgins", "bgint", "bgio", "bgiost", "bgiot", "bgno", "bgnos", "bgo", "bgos", "bi", "bino", "binos", "binost", "binot", "bins", "bios", "biost", "biot", "bis", "bist", "bit", "bno", "bnos", "bo", "bos", "bost", "bot", "gin", "gino", "ginos", "ginost", "ginot", "gins", "ginst", "gint", "giost", "giot", "gis", "gist", "gno", "gnos", "gnost", "gnot", "gost", "ino", "inos", "inost", "inot", "ins", "inst", "int", "iost", "ist", "it", "no", "nos", "nost", "not", "ost", "ot"], "bginot": ["bginot", "bgin", "bgino", "bgint", "bgio", "bgiot", "bgno", "bgo", "bi", "bino", "binot", "biot", "bit", "bno", "bo", "bot", "gin", "gino", "ginot", "gint", "giot", "gno", "gnot", "ino", "inot", "int", "it", "no", "not", "ot"], "bginoz": ["bginoz", "bgin", "bgino", "bgio", "bgno", "bgo", "bi", "bino", "bno", "bo", "boz", "gin", "gino", "ginoz", "ginz", "gno", "gnoz", "ino", "no", "noz"], "bginop": ["bginop", "bgin", "bgino", "bgio", "bgno", "bgo", "bi", "bino", "bno", "bo", "gin", "gino", "ginop", "ginp", "gno", "gnop", "gop", "ino", "inop", "inp", "no", "nop", "op"], "bginor": ["bginor", "bgin", "bgino", "bginr", "bgio", "bgir", "bgno", "bgo", "bgor", "bi", "bino", "binor", "bior", "bir", "bno", "bnor", "bo", "bor", "gin", "gino", "ginor", "ginr", "gior", "gir", "gno", "gnor", "gor", "ino", "inor", "no"], "bginorw": ["bginorw", "bgin", "bgino", "bginor", "bginow", "bginr", "bgio", "bgir", "bgiw", "bgno", "bgo", "bgor", "bi", "bino", "binor", "bior", "bir", "bno", "bnor", "bnorw", "bo", "bor", "borw", "bow", "gin", "gino", "ginor", "ginorw", "ginow", "ginr", "ginrw", "ginw", "gior", "gir", "gno", "gnor", "gnorw", "gnow", "gor", "gorw", "ino", "inor", "inow", "no", "norw"], "bginos": ["bginos", "bgin", "bgino", "bgins", "bgio", "bgno", "bgnos", "bgo", "bgos", "bi", "bino", "binos", "bins", "bios", "bis", "bno", "bnos", "bo", "bos", "gin", "gino", "ginos", "gins", "gis", "gno", "gnos", "ino", "inos", "ins", "no", "nos"], "bginosu": ["bginosu", "bgin", "bgino", "bginos", "bgins", "bginsu", "bginu", "bgio", "bgiosu", "bgiu", "bgno", "bgnos", "bgnsu", "bgnu", "bgo", "bgos", "bgosu", "bgsu", "bi", "bino", "binos", "binosu", "binou", "bins", "binsu", "binu", "bios", "bis", "bno", "bnos", "bnosu", "bnsu", "bo", "bos", "bou", "bsu", "gin", "gino", "ginos", "ginosu", "ginou", "gins", "ginsu", "ginu", "gis", "gno", "gnos", "gnsu", "ino", "inos", "inosu", "inou", "ins", "insu", "no", "nos", "nosu", "nou", "nsu", "osu", "su"], "bginow": ["bginow", "bgin", "bgino", "bgio", "bgiw", "bgno", "bgo", "bi", "bino", "bno", "bo", "bow", "gin", "gino", "ginow", "ginw", "gno", "gnow", "ino", "inow", "no"], "bginosw": ["bginosw", "bgin", "bgino", "bginos", "bginow", "bgins", "bgio", "bgisw", "bgiw", "bgno", "bgnos", "bgo", "bgos", "bi", "bino", "binos", "bins", "bios", "bis", "bno", "bnos", "bo", "bos", "bosw", "bow", "gin", "gino", "ginos", "ginosw", "ginow", "gins", "ginsw", "ginw", "gis", "gisw", "gno", "gnos", "gnosw", "gnow", "gosw", "ino", "inos", "inosw", "inow", "ins", "insw", "isw", "no", "nos", "nosw", "osw"], "bginox": ["bginox", "bgin", "bgino", "bgio", "bgno", "bgo", "bi", "bino", "binox", "bno", "bo", "gin", "gino", "ginx", "gno", "ino", "ix", "no"], "bginrs": ["bginrs", "bgin", "bginr", "bgins", "bgir", "bgirs", "bi", "bins", "bir", "birs", "bis", "gin", "ginr", "ginrs", "gins", "gir", "girs", "gis", "ins", "irs"], "bginorz": ["bginorz", "bgin", "bgino", "bginor", "bginoz", "bginr", "bgio", "bgir", "bgno", "bgo", "bgor", "bi", "bino", "binor", "bior", "biorz", "bir", "bno", "bnor", "bo", "bor", "boz", "gin", "gino", "ginor", "ginoz", "ginr", "ginz", "gior", "gir", "gno", "gnor", "gnoz", "gor", "ino", "inor", "no", "noz", "orz"], "bginrsu": ["bginrsu", "bgin", "bginr", "bginrs", "bginru", "bgins", "bginsu", "bginu", "bgir", "bgirs", "bgiu", "bgnsu", "bgnu", "bgrsu", "bgru", "bgsu", "bi", "binrsu", "binru", "bins", "binsu", "binu", "bir", "birs", "bis", "bnrsu", "bnru", "bnsu", "brsu", "bru", "bsu", "gin", "ginr", "ginrs", "ginrsu", "ginru", "gins", "ginsu", "ginu", "gir", "girs", "gis", "gnrsu", "gnru", "gnsu", "grsu", "gru", "inrsu", "inru", "ins", "insu", "irs", "nrsu", "nsu", "rsu", "su"], "bginrtu": ["bginrtu", "bgin", "bginr", "bginru", "bgint", "bgintu", "bginu", "bgir", "bgiu", "bgnu", "bgru", "bi", "binru", "binu", "bir", "birt", "birtu", "bit", "bnrtu", "bnru", "bntu", "brtu", "bru", "btu", "gin", "ginr", "ginrt", "ginrtu", "ginru", "gint", "gintu", "ginu", "gir", "girt", "gnrtu", "gnru", "grtu", "gru", "inrt", "inru", "int", "intu", "it", "itu", "nrtu", "tu"], "bginu": ["bginu", "bgin", "bgiu", "bgnu", "bi", "binu", "gin", "ginu"], "bgintu": ["bgintu", "bgin", "bgint", "bginu", "bgiu", "bgnu", "bi", "binu", "bit", "bntu", "btu", "gin", "gint", "gintu", "ginu", "int", "intu", "it", "itu", "tu"], "bginstu": ["bginstu", "bgin", "bgins", "bginsu", "bgint", "bgintu", "bginu", "bgiu", "bgnsu", "bgnu", "bgsu", "bi", "bins", "binstu", "binsu", "binu", "bis", "bist", "bistu", "bit", "bnstu", "bnsu", "bntu", "bstu", "bsu", "btu", "gin", "gins", "ginst", "ginstu", "ginsu", "gint", "gintu", "ginu", "gis", "gist", "gnstu", "gnsu", "gstu", "ins", "inst", "instu", "insu", "int", "intu", "ist", "istu", "it", "itu", "nstu", "nsu", "stu", "su", "tu"], "bginouy": ["bginouy", "bgin", "bgino", "bginu", "bginuy", "bgio", "bgiu", "bgno", "bgnu", "bgo", "bgoy", "bguy", "bi", "bino", "binou", "binu", "bno", "bnoy", "bnuy", "bo", "bou", "bouy", "boy", "gin", "gino", "ginou", "ginoy", "ginu", "ginuy", "giny", "gioy", "gno", "gnouy", "gnuy", "ino", "inou", "inoy", "iny", "no", "nou"], "bginru": ["bginru", "bgin", "bginr", "bginu", "bgir", "bgiu", "bgnu", "bgru", "bi", "binru", "binu", "bir", "bnru", "bru", "gin", "ginr", "ginru", "ginu", "gir", "gnru", "gru", "inru"], "bginpru": ["bginpru", "bgin", "bginr", "bginru", "bginu", "bgir", "bgiu", "bgnu", "bgru", "bi", "binru", "binu", "bir", "bnru", "bpru", "bru", "gin", "ginp", "ginpr", "ginpru", "ginpu", "ginr", "ginru", "ginu", "gipr", "gir", "gnpu", "gnru", "gru", "inp", "inpr", "inpru", "inpu", "inru", "pru"], "bginruy": ["bginruy", "bgin", "bginr", "bginru", "bginu", "bginuy", "bgir", "bgiu", "bgnu", "bgru", "bgruy", "bguy", "bi", "binru", "binry", "binu", "bir", "bnru", "bnuy", "bru", "bruy", "gin", "ginr", "ginru", "ginu", "ginuy", "giny", "gir", "gnru", "gnruy", "gnuy", "gru", "inru", "iny", "nruy"], "bginsu": ["bginsu", "bgin", "bgins", "bginu", "bgiu", "bgnsu", "bgnu", "bgsu", "bi", "bins", "binsu", "binu", "bis", "bnsu", "bsu", "gin", "gins", "ginsu", "ginu", "gis", "gnsu", "ins", "insu", "nsu", "su"], "bginsuy": ["bginsuy", "bgin", "bgins", "bginsu", "bginu", "bginuy", "bgiu", "bgnsu", "bgnu", "bgsu", "bguy", "bi", "bins", "binsu", "binu", "bis", "bnsu", "bnuy", "bsu", "bsuy", "gin", "gins", "ginsu", "ginsuy", "ginu", "ginuy", "giny", "gis", "gnsu", "gnuy", "gsuy", "ins", "insu", "iny", "isy", "nsu", "nsuy", "su"], "bginotu": ["bginotu", "bgin", "bgino", "bginot", "bgint", "bgintu", "bginu", "bgio", "bgiot", "bgiu", "bgno", "bgnu", "bgo", "bi", "bino", "binot", "binou", "binu", "biot", "bit", "bno", "bnotu", "bntu", "bo", "bot", "botu", "bou", "btu", "gin", "gino", "ginot", "ginotu", "ginou", "gint", "gintu", "ginu", "giot", "gno", "gnot", "gnotu", "gotu", "ino", "inot", "inotu", "inou", "int", "intu", "it", "itu", "no", "not", "notu", "nou", "ot", "otu", "tu"], "bginuy": ["bginuy", "bgin", "bginu", "bgiu", "bgnu", "bguy", "bi", "binu", "bnuy", "gin", "ginu", "ginuy", "giny", "gnuy", "iny"], "bginuz": ["bginuz", "bgin", "bginu", "bgiu", "bgnu", "bi", "binu", "buz", "gin", "ginu", "ginz"], "bginort": ["bginort", "bgin", "bgino", "bginor", "bginot", "bginr", "bgint", "bgio", "bgiot", "bgir", "bgno", "bgo", "bgor", "bi", "bino", "binor", "binot", "bior", "biort", "biot", "bir", "birt", "bit", "bno", "bnor", "bo", "bor", "bort", "bot", "gin", "gino", "ginor", "ginort", "ginot", "ginr", "ginrt", "gint", "gior", "giot", "gir", "girt", "gno", "gnor", "gnort", "gnot", "gor", "gort", "ino", "inor", "inort", "inot", "inrt", "int", "iort", "it", "no", "nort", "not", "ort", "ot"], "bginopr": ["bginopr", "bgin", "bgino", "bginop", "bginor", "bginr", "bgio", "bgir", "bgno", "bgo", "bgor", "bi", "bino", "binor", "bior", "bir", "bno", "bnor", "bo", "bopr", "bor", "gin", "gino", "ginop", "ginopr", "ginor", "ginp", "ginpr", "ginr", "giopr", "gior", "gipr", "gir", "gno", "gnop", "gnopr", "gnor", "gop", "gopr", "gor", "ino", "inop", "inopr", "inor", "inp", "inpr", "iopr", "no", "nop", "nopr", "op", "opr"], "bginors": ["bginors", "bgin", "bgino", "bginor", "bginos", "bginr", "bginrs", "bgins", "bgio", "bgir", "bgirs", "bgno", "bgnos", "bgo", "bgor", "bgos", "bi", "bino", "binor", "binors", "binos", "bins", "bior", "bios", "bir", "birs", "bis", "bno", "bnor", "bnos", "bo", "bor", "bors", "bos", "gin", "gino", "ginor", "ginors", "ginos", "ginr", "ginrs", "gins", "gior", "giors", "gir", "girs", "gis", "gno", "gnor", "gnors", "gnos", "gor", "gors", "ino", "inor", "inors", "inos", "ins", "iors", "irs", "no", "nors", "nos"], "bginoux": ["bginoux", "bgin", "bgino", "bginox", "bginu", "bgio", "bgiu", "bgno", "bgnu", "bgo", "bi", "bino", "binou", "binox", "binu", "bno", "bnoux", "bo", "bou", "gin", "gino", "ginou", "ginu", "ginx", "gno", "ino", "inou", "ix", "no", "nou"]}