{"chlnoty": ["chlnoty", "chlny", "chlot", "chno", "chnot", "cho", "chot", "clno", "clnoy", "clo", "clot", "cloy", "cno", "cnot", "cnoty", "cnoy", "co", "cot", "hlot", "hloty", "hloy", "hot", "hoty", "lno", "lnoy", "lo", "lot", "loty", "loy", "no", "not", "noty", "ot"], "chlnop": ["chlnop", "chno", "chnop", "cho", "chop", "clno", "clo", "clop", "cno", "co", "cop", "hlnop", "hlop", "hnop", "hop", "lno", "lo", "lop", "no", "nop", "op"], "chlnops": ["chlnops", "chlnop", "chlos", "chno", "chnop", "chnops", "chnos", "cho", "chop", "chops", "chos", "chs", "clno", "clnos", "clo", "clop", "clops", "clos", "cno", "cnos", "co", "cop", "cops", "cos", "hlnop", "hlop", "hlops", "hlos", "hnop", "hnops", "hnos", "hop", "hops", "hos", "lno", "lnos", "lo", "lop", "lops", "los", "no", "nop", "nops", "nos", "op", "ops"], "chlnopy": ["chlnopy", "chlnop", "chlny", "chno", "chnop", "cho", "chop", "chopy", "clno", "clnoy", "clo", "clop", "cloy", "cno", "cnopy", "cnoy", "co", "cop", "copy", "hlnop", "hlnopy", "hlop", "hlopy", "hloy", "hnop", "hnopy", "hop", "hopy", "lno", "lnopy", "lnoy", "lo", "lop", "lopy", "loy", "no", "nop", "nopy", "op", "opy"], "chlnu": ["chlnu", "chlu", "chnu", "clu", "hlu", "lnu", "lu"], "chlny": ["chlny"]}