{"gintu": ["gintu", "gin", "gint", "ginu", "int", "intu", "it", "itu", "tu"], "gint": ["gint", "gin", "int", "it"], "gintv": ["gintv", "gin", "gint", "ginv", "int", "intv", "it", "iv"], "gintw": ["gintw", "gin", "gint", "ginw", "gitw", "int", "intw", "it", "itw"], "ginty": ["ginty", "gin", "gint", "giny", "int", "inty", "iny", "it", "ity"], "gintuv": ["gintuv", "gin", "gint", "gintu", "gintv", "ginu", "ginv", "int", "intu", "intv", "inuv", "it", "itu", "iv", "tu"], "gintuz": ["gintuz", "gin", "gint", "gintu", "ginu", "ginz", "int", "intu", "it", "itu", "itz", "tu"], "gintuw": ["gintuw", "gin", "gint", "gintu", "gintw", "ginu", "ginw", "gitw", "int", "intu", "intw", "it", "itu", "itw", "tu"], "gintuy": ["gintuy", "gin", "gint", "gintu", "ginty", "ginu", "ginuy", "giny", "gnuy", "gtuy", "int", "intu", "intuy", "inty", "iny", "it", "itu", "ity", "ntuy", "tu", "tuy"]}