{"denp": ["deepen", "deepened", "depend", "depended", "pend", "pended", "penned"], "denps": ["deepens", "deepness", "depends", "pends", "spend", "spends"], "denpt": ["dependent", "pendent"], "denpst": ["dependents", "pendents", "steepened"], "denpx": ["expend", "expended"], "denprx": ["expender"], "denprsx": ["expenders"], "denpsx": ["expends"], "denpr": ["perpend", "preened", "prepend"], "denprst": ["presented", "pretenders", "pretends", "represented"], "denprt": ["pretend", "pretended", "pretender", "repented", "repetend"], "denprtv": ["prevented"], "denprtu": ["prudent", "uptrend", "upturned"], "denpru": ["pruned"], "denpu": ["punned", "upend", "upended"], "denptu": ["punted"], "denpw": ["pwned"], "denprs": ["spender", "spenders"], "denprsu": ["spurned", "superdense", "suspender", "suspenders", "underspend", "unpressed", "unrepressed", "unsuppressed"], "denpsu": ["suspend", "suspended", "suspends", "upends"], "denpux": ["unexpended"]}