{"aeklos": ["alkaloses"], "aekln": ["alkane", "alkene", "ankle"], "aeklns": ["alkanes", "alkenes", "ankles", "lankness"], "aeklnt": ["alkanet", "anklet"], "aeklnst": ["alkanets", "anklets", "lankest"], "aeklny": ["alkyne"], "aekltu": ["auklet"], "aeklstu": ["auklets"], "aeklsty": ["eyestalk"], "aekl": ["kale", "lake", "leak"], "aeklnw": ["knawel"], "aeklnsw": ["knawels"], "aeklr": ["laker", "larker", "leaker"], "aekls": ["lakes", "leaks", "slake", "slakes"], "aeklnr": ["lanker", "rankle"], "aeklt": ["latke", "teakettle"], "aeklst": ["latkes", "skeletal", "teakettles"], "aeklmrw": ["lawmaker"], "aekly": ["leaky"], "aeklmry": ["malarkey"], "aeklnrs": ["rankles"], "aeklost": ["skatole"], "aeklpsw": ["sleepwalk", "sleepwalks"], "aeklprs": ["sparkle", "sparkler", "sparklers", "sparkles"], "aeklrst": ["stalker", "stalkers", "talkers"], "aeklrt": ["talker"], "aeklmrt": ["telemark", "telemarketer"], "aeklsw": ["wakeless"], "aeklrw": ["walker"], "aeklrsw": ["walkers"], "aeklwy": ["weakly"]}