{"aimorsu": ["aimorsu", "aimos"], "aimost": ["aimost", "aimos"], "aimorst": ["aimorst", "aimort", "aimos", "aimost"], "aimopsx": ["aimopsx", "aimos", "aimosx", "aimox"], "aimoprs": ["aimoprs", "aimos"], "aimostu": ["aimostu", "aimos", "aimost"], "aimox": ["aimox"], "aimosx": ["aimosx", "aimos", "aimox"], "aimort": ["aimort"], "aimopst": ["aimopst", "aimopt", "aimos", "aimost"], "aimos": ["aimos"], "aimortu": ["aimortu", "aimort"], "aimortv": ["aimortv", "aimort"], "aimopy": ["aimopy"], "aimopt": ["aimopt"], "aimoruv": ["aimoruv"]}