{"beglno": ["beglno", "begl", "beglo"], "beglnos": ["beglnos", "begl", "beglno", "beglo", "beglos", "begls"], "beglor": ["beglor", "begl", "beglo"], "beglors": ["beglors", "begl", "beglo", "beglor", "beglos", "begls"], "beglnu": ["beglnu", "begl", "beglu"], "beglnru": ["beglnru", "begl", "beglnu", "beglru", "beglu"], "beglo": ["beglo", "begl"], "beglos": ["beglos", "begl", "beglo", "begls"], "beglot": ["beglot", "begl", "beglo"], "beglort": ["beglort", "begl", "beglo", "beglor", "beglot"], "beglost": ["beglost", "begl", "beglo", "beglos", "beglot", "begls"], "beglow": ["beglow", "begl", "beglo"], "beglosw": ["beglosw", "begl", "beglo", "beglos", "beglow", "begls"], "beglmu": ["beglmu", "begl", "beglu"], "beglu": ["beglu", "begl"], "beglru": ["beglru", "begl", "beglu"], "beglrsu": ["beglrsu", "begl", "beglru", "begls", "beglsu", "beglu"], "beglsu": ["beglsu", "begl", "begls", "beglu"], "beglosu": ["beglosu", "begl", "beglo", "beglos", "beglou", "begls", "beglsu", "beglu"], "beglnsu": ["beglnsu", "begl", "beglnu", "begls", "beglsu", "beglu"], "begl": ["begl"], "begls": ["begls", "begl"], "beglou": ["beglou", "begl", "beglo", "beglu"], "beglnrt": ["beglnrt", "begl"], "beglmru": ["beglmru", "begl", "beglmu", "beglru", "beglu"], "beglmtu": ["beglmtu", "begl", "beglmu", "beglu"]}