{"defhimu": ["defhimu", "defhu"], "defhirt": ["defhirt", "defht"], "defhins": ["defhins", "defhis"], "defhis": ["defhis"], "defhls": ["defhls"], "defhlsu": ["defhlsu", "defhls", "defhlu", "defhu"], "defhlor": ["defhlor", "defho"], "defhlrw": ["defhlrw"], "defhnrs": ["defhnrs", "defhrs"], "defhort": ["defhort", "defho", "defhot", "defht"], "defhrtu": ["defhrtu", "defht", "defhu"], "defhlu": ["defhlu", "defhu"], "defhluy": ["defhluy", "defhlu", "defhu"], "defht": ["defht"], "defho": ["defho"], "defhior": ["defhior", "defho"], "defhot": ["defhot", "defho", "defht"], "defhu": ["defhu"], "defhirs": ["defhirs", "defhis", "defhrs"], "defhrs": ["defhrs"], "defhlos": ["defhlos", "defhls", "defho"], "defhist": ["defhist", "defhis", "defht"], "defhlnu": ["defhlnu", "defhlu", "defhu"], "defhiw": ["defhiw"], "defhlow": ["defhlow", "defho"], "defhiow": ["defhiow", "defhiw", "defho"]}