{"dghot": ["dghot", "dgho", "dgo", "dho", "dhot", "do", "ghot", "hot", "ot"], "dghou": ["dghou", "dgho", "dgo", "dho", "do", "ghou"], "dghosu": ["dghosu", "dgho", "dghou", "dgo", "dgos", "dho", "dhos", "do", "dos", "dosu", "dsu", "ghos", "ghosu", "ghou", "ghsu", "hos", "hsu", "osu", "su"], "dghotuy": ["dghotuy", "dgho", "dghot", "dghou", "dghouy", "dgo", "dgotu", "dgoy", "dho", "dhot", "dhtu", "do", "dotu", "doty", "dtuy", "ghot", "ghotu", "ghou", "ghoy", "ghtu", "gotu", "gotuy", "gtuy", "hot", "hotu", "hotuy", "hoty", "ot", "otu", "tu", "tuy"], "dghouy": ["dghouy", "dgho", "dghou", "dgo", "dgoy", "dho", "do", "ghou", "ghoy"], "dghortu": ["dghortu", "dgho", "dghot", "dghou", "dgo", "dgort", "dgoru", "dgotu", "dgru", "dho", "dhot", "dhtu", "do", "dor", "dort", "dortu", "doru", "dotu", "drtu", "dru", "ghortu", "ghoru", "ghot", "ghotu", "ghou", "ghtu", "gor", "gort", "gortu", "gotu", "grtu", "gru", "hor", "hort", "horu", "hot", "hotu", "hrtu", "ort", "ortu", "ot", "otu", "tu"], "dgho": ["dgho", "dgo", "dho", "do"], "dghorsu": ["dghorsu", "dgho", "dghosu", "dghou", "dgo", "dgorsu", "dgoru", "dgos", "dgrsu", "dgru", "dho", "dhorsu", "dhos", "dhrsu", "do", "dor", "dors", "dorsu", "doru", "dos", "dosu", "drsu", "dru", "dsu", "ghorsu", "ghoru", "ghos", "ghosu", "ghou", "ghrsu", "ghsu", "gor", "gors", "grsu", "gru", "hor", "hors", "horsu", "horu", "hos", "hrsu", "hsu", "orsu", "osu", "rsu", "su"]}