{"egnpr": ["egnpr", "egn", "egnp", "egnr", "egpr", "egr", "enp", "enpr", "enr", "ep", "epr"], "egnprs": ["egnprs", "egn", "egnp", "egnpr", "egnr", "egnrs", "egns", "egpr", "egprs", "egps", "egr", "egrs", "egs", "enp", "enpr", "enprs", "enps", "enr", "enrs", "ens", "ep", "epr", "eprs", "eps", "ers", "es"], "egnpux": ["egnpux", "egn", "egnp", "egnpu", "egnu", "enp", "enpu", "ep", "gnpu"], "egnprux": ["egnprux", "egn", "egnp", "egnpr", "egnpru", "egnpu", "egnpux", "egnr", "egnru", "egnu", "egpr", "egpru", "egprx", "egr", "egru", "egrux", "egrx", "enp", "enpr", "enpru", "enpu", "enr", "enru", "ep", "epr", "epru", "gnpu", "gnru", "gru", "pru"], "egnpsux": ["egnpsux", "egn", "egnp", "egnpu", "egnpux", "egns", "egnsu", "egnu", "egps", "egs", "egsu", "egsx", "enp", "enps", "enpsu", "enpsx", "enpu", "ens", "ensu", "ensux", "ep", "eps", "epsu", "es", "esu", "esx", "gnpsu", "gnpu", "gnsu", "gpsu", "npsu", "nsu", "psu", "su"], "egnp": ["egnp", "egn", "enp", "ep"], "egnptu": ["egnptu", "egn", "egnp", "egnpu", "egnt", "egntu", "egnu", "egptu", "enp", "enpt", "enptu", "enpu", "ent", "entu", "ep", "ept", "eptu", "gnpu", "nptu", "ptu", "tu"], "egnpru": ["egnpru", "egn", "egnp", "egnpr", "egnpu", "egnr", "egnru", "egnu", "egpr", "egpru", "egr", "egru", "enp", "enpr", "enpru", "enpu", "enr", "enru", "ep", "epr", "epru", "gnpu", "gnru", "gru", "pru"], "egnprsu": ["egnprsu", "egn", "egnp", "egnpr", "egnprs", "egnpru", "egnpu", "egnr", "egnrs", "egnrsu", "egnru", "egns", "egnsu", "egnu", "egpr", "egprs", "egprsu", "egpru", "egps", "egr", "egrs", "egrsu", "egru", "egs", "egsu", "enp", "enpr", "enprs", "enprsu", "enpru", "enps", "enpsu", "enpu", "enr", "enrs", "enrsu", "enru", "ens", "ensu", "ep", "epr", "eprs", "eprsu", "epru", "eps", "epsu", "ers", "ersu", "es", "esu", "gnprsu", "gnpsu", "gnpu", "gnrsu", "gnru", "gnsu", "gpsu", "grsu", "gru", "nprsu", "npsu", "nrsu", "nsu", "prsu", "pru", "psu", "rsu", "su"], "egnpu": ["egnpu", "egn", "egnp", "egnu", "enp", "enpu", "ep", "gnpu"]}